appium_python_client_shadowstep-0.36.16.dist-info/licenses/LICENSE
appium_python_client_shadowstep-0.36.16.dist-info/licenses/LICENSES_THIRD_PARTY.md
shadowstep/__init__.py
shadowstep/enums.py
shadowstep/page_base.py
shadowstep/py.typed
shadowstep/shadowstep.py
shadowstep/shadowstep_base.py
shadowstep/decorators/__init__.py
shadowstep/decorators/decorators.py
shadowstep/decorators/element_decorators.py
shadowstep/decorators/image_decorators.py
shadowstep/decorators/shadowstep_decorators.py
shadowstep/element/__init__.py
shadowstep/element/actions.py
shadowstep/element/base.py
shadowstep/element/conditions.py
shadowstep/element/coordinates.py
shadowstep/element/dom.py
shadowstep/element/element.py
shadowstep/element/gestures.py
shadowstep/element/properties.py
shadowstep/element/screenshots.py
shadowstep/element/should.py
shadowstep/element/utilities.py
shadowstep/element/waiting.py
shadowstep/exceptions/__init__.py
shadowstep/exceptions/shadowstep_exceptions.py
shadowstep/image/__init__.py
shadowstep/image/image.py
shadowstep/image/should.py
shadowstep/locator/__init__.py
shadowstep/locator/ui_selector.py
shadowstep/locator/converter/__init__.py
shadowstep/locator/converter/dict_converter.py
shadowstep/locator/converter/locator_converter.py
shadowstep/locator/converter/ui_selector_converter.py
shadowstep/locator/converter/xpath_converter.py
shadowstep/locator/converter/ui_selector_converter_core/__init__.py
shadowstep/locator/converter/ui_selector_converter_core/ui_selector_ast.py
shadowstep/locator/converter/ui_selector_converter_core/ui_selector_lexer.py
shadowstep/locator/converter/ui_selector_converter_core/ui_selector_parser.py
shadowstep/locator/locator_types/__init__.py
shadowstep/locator/locator_types/shadowstep_dict.py
shadowstep/locator/locator_types/ui_selector.py
shadowstep/locator/locator_types/xpath.py
shadowstep/locator/map/__init__.py
shadowstep/locator/map/dict_to_ui.py
shadowstep/locator/map/dict_to_xpath.py
shadowstep/locator/map/ui_to_dict.py
shadowstep/locator/map/ui_to_xpath.py
shadowstep/locator/map/xpath_to_dict.py
shadowstep/locator/map/xpath_to_ui.py
shadowstep/logcat/__init__.py
appium_python_client_shadowstep-0.36.16.dist-info/METADATA
appium_python_client_shadowstep-0.36.16.dist-info/WHEEL
appium_python_client_shadowstep-0.36.16.dist-info/top_level.txt
appium_python_client_shadowstep-0.36.16.dist-info/RECORD
