Metadata-Version: 2.4
Name: appium-python-client-shadowstep
Version: 0.36.16
Summary: UI Testing Framework powered by Appium Python Client
Author-email: Molokov Klim <ultrakawaii9654449192@gmail.com>
License-Expression: MIT
Project-URL: Repository, https://github.com/molokov-klim/Appium-Python-Client-Shadowstep
Keywords: appium,testing,uiautomator2,android,automation,framework
Classifier: Programming Language :: Python :: 3.9
Classifier: Programming Language :: Python :: 3.11
Classifier: Programming Language :: Python :: 3.12
Classifier: Programming Language :: Python :: 3.13
Requires-Python: >=3.9
License-File: LICENSE
License-File: LICENSES_THIRD_PARTY.md
Requires-Dist: Appium-Python-Client>=5.2.2
Requires-Dist: selenium>=4.36
Requires-Dist: websocket-client>=1.8.0
Requires-Dist: requests>=2.31.0
Requires-Dist: opencv-python>=4.12.0.88
Requires-Dist: numpy>=2.0.0
Requires-Dist: Pillow>=11.3.0
Requires-Dist: pytesseract>=0.3.10
Requires-Dist: allure-pytest>=2.13.2
Requires-Dist: paramiko>=4.0.0
Requires-Dist: scp>=0.14.5
Requires-Dist: networkx>=3.2.1
Requires-Dist: lxml>=6.0.2
Requires-Dist: jinja2>=3.1.6
Requires-Dist: anyascii>=0.3.3
Requires-Dist: eulxml>=1.1.3
Requires-Dist: setuptools==80.9.0
Requires-Dist: wheel>=0.45.1
Requires-Dist: pyright>=1.1.405
Requires-Dist: ruff>=0.13.2
Dynamic: license-file
